hcli_problem_details/__init__.py
hcli_problem_details/package.py
hcli_problem_details/rfc9457.py
hcli_problem_details-0.2.0.dist-info/licenses/LICENSE.txt
hcli_problem_details-0.2.0.dist-info/METADATA
hcli_problem_details-0.2.0.dist-info/WHEEL
hcli_problem_details-0.2.0.dist-info/top_level.txt
hcli_problem_details-0.2.0.dist-info/RECORD
