Metadata-Version: 2.4
Name: hcli_problem_details
Version: 0.2.0
Summary: RFC9457 compliant problem details for HCLI applications
Author-email: Jeff Michaud <cometaj2@proton.me>
License-Expression: MIT
Project-URL: Homepage, https://github.com/cometaj2/hcli_problem_details
Keywords: hcli,rfc9457,problem-details,exceptions,http,errors,http
Classifier: Development Status :: 4 - Beta
Classifier: Intended Audience :: Developers
Classifier: Topic :: Software Development
Classifier: Programming Language :: Python :: 3.8
Classifier: Programming Language :: Python :: 3.9
Classifier: Programming Language :: Python :: 3.10
Classifier: Programming Language :: Python :: 3.11
Classifier: Programming Language :: Python :: 3.12
License-File: LICENSE.txt
Dynamic: license-file
